ScrapyJdAzw/__init__.py
ScrapyJdAzw/items.py
ScrapyJdAzw/pipelines.py
ScrapyJdAzw/settings.py
ScrapyJdAzw/spiders/__init__.py
ScrapyJdAzw/spiders/jdazwspider.py
ScrapyJD-1.0.2.dist-info/LICENSE
ScrapyJD-1.0.2.dist-info/METADATA
ScrapyJD-1.0.2.dist-info/WHEEL
ScrapyJD-1.0.2.dist-info/top_level.txt
ScrapyJD-1.0.2.dist-info/RECORD
